{"total":230,"cards":[{"cardRace":"rare","standard":1,"flavorText":"龙虾龙虾两只爪，左右一夹就变大。","collectible":1,"keywords":["battlecry"],"battlegrounds":null,"keywordIds":[8],"pic":"https://hearthstone.nosdn.127.net/hearthstone/0aef9503fcbeb6a3ab5df3c8ce58519950226f7adb5d91519001e6ded03ee83d.png","spellSchoolId":null,"childCards":null,"childIds":null,"multiClassIds":[],"golden":0,"id":56417,"cardTypeId":4,"text":"<b>战吼：</b> 将相邻的随从随机变形成为法力值消耗增加（1）点的随从。","cardClass":"shaman","slug":"56417-bogstrok-clacker","image":"https://hearthstone.nosdn.127.net/hearthstone/0aef9503fcbeb6a3ab5df3c8ce58519950226f7adb5d91519001e6ded03ee83d.png","neutralClass":null,"durability":null,"rarityId":3,"dustValue":null,"armor":null,"background":"龙虾龙虾两只爪，左右一夹就变大。","cardSet":"ashes-of-outland","craftingCost":null,"cardId":56417,"availableGameModes":["constructed","arena"],"name":"泥沼巨钳龙虾人","parentCard":null,"ids":null,"legacyKeywords":"随从,稀有,外域,萨满祭司,战吼","code":"56417-bogstrok-clacker","artist":"Luca Zontini","description":"<b>战吼：</b> 将相邻的随从随机变形成为法力值消耗增加（1）点的随从。","consume":0,"cropImage":"https://hearthstone.nosdn.127.net/hearthstone/b3eff631b18c5931dfbba7266c7cd3e78c32c72940a31614317c67585b3e7b6a.png","gain":0,"classId":8,"cardEffect":"battlecry","tier":null,"attack":3,"imageUrl":"https://hearthstone.nosdn.127.net/hearthstone/0aef9503fcbeb6a3ab5df3c8ce58519950226f7adb5d91519001e6ded03ee83d.png","cardRarity":"rare","cardSetId":1414,"minionTypeId":null,"cost":3,"cardCode":"","cardType":"minion","standardCard":true,"health":3,"updateTime":null,"classicCard":false,"parentId":null,"cardMultiClass":[],"createTime":null,"minionType":null,"imageGold":"","artistName":"Luca Zontini","availableClassIds":[8],"manaCost":3,"wildCard":true},{"cardRace":"legendary","standard":0,"flavorText":"平静，祥和，仿佛看到……一群青蛙。","collectible":1,"keywords":[],"battlegrounds":null,"keywordIds":null,"pic":"https://hearthstone.nosdn.127.net/hearthstone/1bd41fc61283b9ec9329b0143c59ef4d6921e6f4b7d3e5627ab08d62837d0bdd.png","spellSchoolId":null,"childCards":null,"childIds":null,"multiClassIds":[],"golden":0,"id":49867,"cardTypeId":4,"text":"每当你以一个随从为目标施放法术时，对该随从相邻的随从再次施放。","cardClass":"shaman","slug":"49867-zentimo","image":"https://hearthstone.nosdn.127.net/hearthstone/1bd41fc61283b9ec9329b0143c59ef4d6921e6f4b7d3e5627ab08d62837d0bdd.png","neutralClass":null,"durability":null,"rarityId":5,"dustValue":null,"armor":null,"background":"平静，祥和，仿佛看到……一群青蛙。","cardSet":"rastakhans-rumble","craftingCost":null,"cardId":49867,"availableGameModes":["constructed"],"name":"泽蒂摩","parentCard":null,"ids":null,"legacyKeywords":"随从,传说,大乱斗,萨满祭司","code":"49867-zentimo","artist":"Evgeniy Zagumyennyy","description":"每当你以一个随从为目标施放法术时，对该随从相邻的随从再次施放。","consume":0,"cropImage":"https://hearthstone.nosdn.127.net/hearthstone/938a5c1005fbc65ada72f178f3ea11d0f961878301a8d56ae54a0e8fe3c5d330.png","gain":0,"classId":8,"cardEffect":"","tier":null,"attack":1,"imageUrl":"https://hearthstone.nosdn.127.net/hearthstone/1bd41fc61283b9ec9329b0143c59ef4d6921e6f4b7d3e5627ab08d62837d0bdd.png","cardRarity":"legendary","cardSetId":1129,"minionTypeId":null,"cost":3,"cardCode":"","cardType":"minion","standardCard":false,"health":3,"updateTime":null,"classicCard":false,"parentId":null,"cardMultiClass":[],"createTime":null,"minionType":null,"imageGold":"https://hearthstone.nosdn.127.net/hearthstone/2f9602ae8a02de90c0065e7e6ace77d68cbe2753c56ebe8c48d64d94cf1bdfbf.png","artistName":"Evgeniy Zagumyennyy","availableClassIds":[8],"manaCost":3,"wildCard":true},{"cardRace":"common","standard":0,"flavorText":"事实证明海象人对于图腾的样式一点都不挑剔。","collectible":1,"keywords":["battlecry"],"battlegrounds":null,"keywordIds":[8],"pic":"https://hearthstone.nosdn.127.net/hearthstone/2ded9e6e5116d8eb2a8497c7858be1d9e9474b5872a93b58edb4ec3be1c17e33.png","spellSchoolId":null,"childCards":null,"childIds":null,"multiClassIds":[],"golden":0,"id":2513,"cardTypeId":4,"text":"<b>战吼：</b>随机召唤一个基础图腾。","cardClass":"shaman","slug":"2513-tuskarr-totemic","image":"https://hearthstone.nosdn.127.net/hearthstone/2ded9e6e5116d8eb2a8497c7858be1d9e9474b5872a93b58edb4ec3be1c17e33.png","neutralClass":null,"durability":null,"rarityId":1,"dustValue":null,"armor":null,"background":"事实证明海象人对于图腾的样式一点都不挑剔。","cardSet":"tgt","craftingCost":null,"cardId":2513,"availableGameModes":["constructed"],"name":"海象人图腾师","parentCard":null,"ids":null,"legacyKeywords":"随从,普通,冠军的试炼,萨满祭司,战吼","code":"2513-tuskarr-totemic","artist":"Eva Widermann","description":"<b>战吼：</b>随机召唤一个基础图腾。","consume":0,"cropImage":"https://hearthstone.nosdn.127.net/hearthstone/e2792e57dcd7f53a0441502eaafe8d38116db1d932543b64b23616db323186e4.jpg","gain":0,"classId":8,"cardEffect":"battlecry","tier":null,"attack":3,"imageUrl":"https://hearthstone.nosdn.127.net/hearthstone/2ded9e6e5116d8eb2a8497c7858be1d9e9474b5872a93b58edb4ec3be1c17e33.png","cardRarity":"common","cardSetId":15,"minionTypeId":null,"cost":3,"cardCode":"","cardType":"minion","standardCard":false,"health":2,"updateTime":null,"classicCard":false,"parentId":null,"cardMultiClass":[],"createTime":null,"minionType":null,"imageGold":"","artistName":"Eva Widermann","availableClassIds":[8],"manaCost":3,"wildCard":true},{"cardRace":"common","standard":0,"flavorText":"他很怀念当年和他一起守关的299位小伙伴。","collectible":1,"keywords":["taunt","battlecry"],"battlegrounds":null,"keywordIds":[1,8],"pic":"https://hearthstone.nosdn.127.net/hearthstone/e25294e051c0e977c55e020b4ba035bc620c207157f683b29d5a5ba36e711cf6.png","spellSchoolId":null,"childCards":null,"childIds":null,"multiClassIds":[],"golden":0,"id":41479,"cardTypeId":4,"text":"<b>嘲讽，战吼：</b> 恢复 3点生命值。","cardClass":"shaman","slug":"41479-hot-spring-guardian","image":"https://hearthstone.nosdn.127.net/hearthstone/e25294e051c0e977c55e020b4ba035bc620c207157f683b29d5a5ba36e711cf6.png","neutralClass":null,"durability":null,"rarityId":1,"dustValue":null,"armor":null,"background":"他很怀念当年和他一起守关的299位小伙伴。","cardSet":"ungoro","craftingCost":null,"cardId":41479,"availableGameModes":["constructed","duels"],"name":"温泉守卫","parentCard":null,"ids":null,"legacyKeywords":"随从,普通,元素,安戈洛,萨满祭司,嘲讽,战吼","code":"41479-hot-spring-guardian","artist":"Gustav Schmidt","description":"<b>嘲讽，战吼：</b> 恢复 3点生命值。","consume":0,"cropImage":"https://hearthstone.nosdn.127.net/hearthstone/6e266903ca13acf3f9008fdbe27881ff986d392535f93996f7c6af884dab3f58.jpg","gain":0,"classId":8,"cardEffect":"taunt,battlecry","tier":null,"attack":2,"imageUrl":"https://hearthstone.nosdn.127.net/hearthstone/e25294e051c0e977c55e020b4ba035bc620c207157f683b29d5a5ba36e711cf6.png","cardRarity":"common","cardSetId":27,"minionTypeId":18,"cost":3,"cardCode":"","cardType":"minion","standardCard":false,"health":4,"updateTime":null,"classicCard":false,"parentId":null,"cardMultiClass":[],"createTime":null,"minionType":"elemental","imageGold":"","artistName":"Gustav Schmidt","availableClassIds":[8],"manaCost":3,"wildCard":true},{"cardRace":"legendary","standard":1,"flavorText":"如果一个讲师在森林中发表了一次无人倾听的演讲，那么实际上她是否发出了声音？","collectible":1,"keywords":["windfury","rush","spellburst"],"battlegrounds":null,"keywordIds":[11,53,88],"pic":"https://hearthstone.nosdn.127.net/hearthstone/e58712f736ffe18588a077cb5e8154f0fdde556c186fa33b77fa1189250c2ada.png","spellSchoolId":null,"childCards":null,"childIds":null,"multiClassIds":[2,8],"golden":0,"id":59253,"cardTypeId":4,"text":"<b>突袭，风怒</b> <b>法术迸发：</b>获得等同于法术法力值消耗的攻击力和生命值。","cardClass":"","slug":"59253-speaker-gidra","image":"https://hearthstone.nosdn.127.net/hearthstone/e58712f736ffe18588a077cb5e8154f0fdde556c186fa33b77fa1189250c2ada.png","neutralClass":null,"durability":null,"rarityId":5,"dustValue":null,"armor":null,"background":"如果一个讲师在森林中发表了一次无人倾听的演讲，那么实际上她是否发出了声音？","cardSet":"scholomance-academy","craftingCost":null,"cardId":59253,"availableGameModes":["constructed","duels"],"name":"演讲者吉德拉","parentCard":null,"ids":null,"legacyKeywords":"随从,传说,通灵学园,中立,德鲁伊,萨满祭司,风怒,突袭,法术迸发","code":"59253-speaker-gidra","artist":"Paul Mafayon","description":"<b>突袭，风怒</b> <b>法术迸发：</b>获得等同于法术法力值消耗的攻击力和生命值。","consume":0,"cropImage":"https://hearthstone.nosdn.127.net/hearthstone/14610f4dbc1d589ad8abfab9ab0335c3376d0c5f14f106e8e6398025f870a7dc.png","gain":0,"classId":12,"cardEffect":"windfury,rush,spellburst","tier":null,"attack":1,"imageUrl":"https://hearthstone.nosdn.127.net/hearthstone/e58712f736ffe18588a077cb5e8154f0fdde556c186fa33b77fa1189250c2ada.png","cardRarity":"legendary","cardSetId":1443,"minionTypeId":null,"cost":3,"cardCode":"","cardType":"minion","standardCard":true,"health":4,"updateTime":null,"classicCard":false,"parentId":null,"cardMultiClass":["druid","shaman"],"createTime":null,"minionType":null,"imageGold":"","artistName":"Paul Mafayon","availableClassIds":[2,8],"manaCost":3,"wildCard":true},{"cardRace":"epic","standard":0,"flavorText":"死亡不是终点，而是新的开始。","collectible":1,"keywords":["deathrattle"],"battlegrounds":null,"keywordIds":[12],"pic":"https://hearthstone.nosdn.127.net/hearthstone/1e4c43ad6041ea6f306eca5442302edfc37e85591ecdfe3314ab7ef0d3afd190.png","spellSchoolId":4,"childCards":null,"childIds":null,"multiClassIds":[],"golden":0,"id":41879,"cardTypeId":5,"text":"使你的所有随从获得“<b>亡语：</b>将该随从移回你的手牌”。","cardClass":"shaman","slug":"41879-spirit-echo","image":"https://hearthstone.nosdn.127.net/hearthstone/1e4c43ad6041ea6f306eca5442302edfc37e85591ecdfe3314ab7ef0d3afd190.png","neutralClass":null,"durability":null,"rarityId":4,"dustValue":null,"armor":null,"background":"死亡不是终点，而是新的开始。","cardSet":"ungoro","craftingCost":null,"cardId":41879,"availableGameModes":["constructed","duels"],"name":"灵魂回响","parentCard":null,"ids":null,"legacyKeywords":"法术,史诗,安戈洛,萨满祭司,亡语","code":"41879-spirit-echo","artist":"Hideaki Takamura","description":"使你的所有随从获得“<b>亡语：</b>将该随从移回你的手牌”。","consume":0,"cropImage":"https://hearthstone.nosdn.127.net/hearthstone/009edf7483cd24d8d3f09bcc495c30798cfffb86285beb3ed09dcacb89cd3ffb.png","gain":0,"classId":8,"cardEffect":"deathrattle","tier":null,"attack":null,"imageUrl":"https://hearthstone.nosdn.127.net/hearthstone/1e4c43ad6041ea6f306eca5442302edfc37e85591ecdfe3314ab7ef0d3afd190.png","cardRarity":"epic","cardSetId":27,"minionTypeId":null,"cost":3,"cardCode":"","cardType":"spell","standardCard":false,"health":null,"updateTime":null,"classicCard":false,"parentId":null,"cardMultiClass":[],"createTime":null,"minionType":null,"imageGold":"","artistName":"Hideaki Takamura","availableClassIds":[8],"manaCost":3,"wildCard":true},{"cardRace":"rare","standard":0,"flavorText":"就像火焰领主吐了一口口水，呃，火。","collectible":1,"keywords":["overload"],"battlegrounds":null,"keywordIds":[14],"pic":"https://hearthstone.nosdn.127.net/hearthstone/95f0ec6948b567eeaf51c6ec5e37dc606f80d370d7ca1bcfe72a9739a7de187f.png","spellSchoolId":2,"childCards":null,"childIds":null,"multiClassIds":[],"golden":0,"id":864,"cardTypeId":5,"text":"造成 5点伤害，<b>过载：</b>（2）","cardClass":"shaman","slug":"864-lava-burst","image":"https://hearthstone.nosdn.127.net/hearthstone/95f0ec6948b567eeaf51c6ec5e37dc606f80d370d7ca1bcfe72a9739a7de187f.png","neutralClass":null,"durability":null,"rarityId":3,"dustValue":null,"armor":null,"background":"就像火焰领主吐了一口口水，呃，火。","cardSet":"legacy","craftingCost":null,"cardId":864,"availableGameModes":["constructed","arena","duels"],"name":"熔岩爆裂","parentCard":null,"ids":null,"legacyKeywords":"法术,稀有,萨满祭司,过载","code":"864-lava-burst","artist":"Dan Scott","description":"造成 5点伤害，<b>过载：</b>（2）","consume":0,"cropImage":"https://hearthstone.nosdn.127.net/hearthstone/e1c5d023d1a366ac520e8dbd075054bb509740b7894daf53f21fd0142dab96d7.png","gain":0,"classId":8,"cardEffect":"overload","tier":null,"attack":null,"imageUrl":"https://hearthstone.nosdn.127.net/hearthstone/95f0ec6948b567eeaf51c6ec5e37dc606f80d370d7ca1bcfe72a9739a7de187f.png","cardRarity":"rare","cardSetId":3,"minionTypeId":null,"cost":3,"cardCode":"","cardType":"spell","standardCard":false,"health":null,"updateTime":null,"classicCard":false,"parentId":null,"cardMultiClass":[],"createTime":null,"minionType":null,"imageGold":"https://hearthstone.nosdn.127.net/hearthstone/4de5a379b64cd9ae434fc10f0ff7346c1f02b2edfa2e83082ab142fe55915a6d.png","artistName":"Dan Scott","availableClassIds":[8],"manaCost":3,"wildCard":true},{"cardRace":"legendary","standard":1,"flavorText":"艾萨拉女王的私人侍女，变成了伊利丹·怒风的副官。兼任发型嘶嘶嘶……师。","collectible":1,"keywords":["spellpower","deathrattle"],"battlegrounds":null,"keywordIds":[2,12],"pic":"https://hearthstone.nosdn.127.net/hearthstone/dd3b285ba74e3f270cc9c44c5c77963df0ac9aac013f91eeb0ac042f22c4f731.png","spellSchoolId":null,"childCards":[{"flavorText":"","collectible":0,"battlegrounds":null,"keywordIds":[2,8],"spellSchoolId":null,"cropImage":"https://hearthstone.nosdn.127.net/hearthstone/b92bb6b21539a918c93b84e882f48e6ce7d428a9a6d2f170f046c1c6829bea9d.jpg","classId":8,"tier":null,"childIds":null,"attack":5,"multiClassIds":[],"cardSetId":1414,"cardTypeId":4,"id":56626,"text":"<b>法术伤害+1</b> <b>战吼：</b>抽三张法术牌，其法力值消耗减少（3）点。","minionTypeId":null,"slug":"56626-vashj-prime","image":"https://hearthstone.nosdn.127.net/hearthstone/d9250fa8f985402258637f4f559caede0bd7099ba3a77e0eab879eab40b2ac42.png","durability":null,"health":4,"parentId":56420,"rarityId":null,"armor":null,"availableGameModes":["constructed"],"name":"终极瓦丝琪","imageGold":"","artistName":"James Ryman","availableClassIds":[8],"manaCost":7}],"childIds":[56626],"multiClassIds":[],"golden":0,"id":56420,"cardTypeId":4,"text":"<b>法术伤害+1</b> <b>亡语：</b>将“终极瓦丝琪”洗入你的牌库。","cardClass":"shaman","slug":"56420-lady-vashj","image":"https://hearthstone.nosdn.127.net/hearthstone/dd3b285ba74e3f270cc9c44c5c77963df0ac9aac013f91eeb0ac042f22c4f731.png","neutralClass":null,"durability":null,"rarityId":5,"dustValue":null,"armor":null,"background":"艾萨拉女王的私人侍女，变成了伊利丹·怒风的副官。兼任发型嘶嘶嘶……师。","cardSet":"ashes-of-outland","craftingCost":null,"cardId":56420,"availableGameModes":["constructed","arena"],"name":"瓦丝琪女士","parentCard":null,"ids":null,"legacyKeywords":"随从,传说,外域,萨满祭司,法术伤害,亡语","code":"56420-lady-vashj","artist":"James Ryman","description":"<b>法术伤害+1</b> <b>亡语：</b>将“终极瓦丝琪”洗入你的牌库。","consume":0,"cropImage":"https://hearthstone.nosdn.127.net/hearthstone/d465c63d5fdfa1e2dc8857370fab4f805443101f53e63fe9a819b5a9329af4b9.png","gain":0,"classId":8,"cardEffect":"spellpower,deathrattle","tier":null,"attack":4,"imageUrl":"https://hearthstone.nosdn.127.net/hearthstone/dd3b285ba74e3f270cc9c44c5c77963df0ac9aac013f91eeb0ac042f22c4f731.png","cardRarity":"legendary","cardSetId":1414,"minionTypeId":null,"cost":3,"cardCode":"","cardType":"minion","standardCard":true,"health":3,"updateTime":null,"classicCard":false,"parentId":null,"cardMultiClass":[],"createTime":null,"minionType":null,"imageGold":"https://hearthstone.nosdn.127.net/hearthstone/dd5adc6b5304383e60620e3ff420d99a7555c1ba91e60cb16397f471c1b0c54c.png","artistName":"James Ryman","availableClassIds":[8],"manaCost":3,"wildCard":true}],"curPage":15,"prePage":14,"nextPage":16,"totalPage":29,"totalPerClass":{"demonhunter":109,"hunter":230,"druid":230,"shaman":230,"paladin":230,"warrior":230,"rogue":232,"mage":231,"priest":237,"warlock":232,"neutral":1048},"pageSize":8,"curCardClass":"shaman"}