{"total":230,"cards":[{"cardRace":"epic","standard":1,"flavorText":"“我要的明明是灰烬使者，不是灰尘使者！”","collectible":1,"keywords":[],"battlegrounds":null,"keywordIds":null,"pic":"https://hearthstone.nosdn.127.net/hearthstone/b8e41fafb2619cce5d47ae302988719cc6a18d720aca3c0888786ff1072c7c94.png","spellSchoolId":null,"childCards":null,"childIds":null,"multiClassIds":[],"golden":0,"id":56443,"cardTypeId":7,"text":"在你的英雄攻击后，随机将一张鱼人牌置入你的手牌。","cardClass":"paladin","slug":"56443-underlight-angling-rod","image":"https://hearthstone.nosdn.127.net/hearthstone/b8e41fafb2619cce5d47ae302988719cc6a18d720aca3c0888786ff1072c7c94.png","neutralClass":null,"durability":2,"rarityId":4,"dustValue":null,"armor":null,"background":"“我要的明明是灰烬使者，不是灰尘使者！”","cardSet":"ashes-of-outland","craftingCost":null,"cardId":56443,"availableGameModes":["constructed","arena"],"name":"幽光鱼竿","parentCard":null,"ids":null,"legacyKeywords":"武器,史诗,外域,圣骑士","code":"56443-underlight-angling-rod","artist":"Jason Kang","description":"在你的英雄攻击后，随机将一张鱼人牌置入你的手牌。","consume":0,"cropImage":"https://hearthstone.nosdn.127.net/hearthstone/0cf0f2bb01915166c093694ce692a10ce45ec0ce22a65789949190206fa22cf4.png","gain":0,"classId":5,"cardEffect":"","tier":null,"attack":3,"imageUrl":"https://hearthstone.nosdn.127.net/hearthstone/b8e41fafb2619cce5d47ae302988719cc6a18d720aca3c0888786ff1072c7c94.png","cardRarity":"epic","cardSetId":1414,"minionTypeId":null,"cost":3,"cardCode":"","cardType":"weapon","standardCard":true,"health":null,"updateTime":null,"classicCard":false,"parentId":null,"cardMultiClass":[],"createTime":null,"minionType":null,"imageGold":"","artistName":"Jason Kang","availableClassIds":[5],"manaCost":3,"wildCard":true},{"cardRace":"common","standard":1,"flavorText":"他整天与战马为伍，终年无休。","collectible":1,"keywords":[],"battlegrounds":null,"keywordIds":null,"pic":"https://hearthstone.nosdn.127.net/hearthstone/f5991ac16ea1c95ed31820996b3b5799e090ef0f8f849c1919b5197817cc4a92.png","spellSchoolId":null,"childCards":null,"childIds":null,"multiClassIds":[],"golden":0,"id":69703,"cardTypeId":4,"text":"你的白银之手新兵获得+1攻击力。","cardClass":"paladin","slug":"69703-warhorse-trainer","image":"https://hearthstone.nosdn.127.net/hearthstone/f5991ac16ea1c95ed31820996b3b5799e090ef0f8f849c1919b5197817cc4a92.png","neutralClass":null,"durability":null,"rarityId":1,"dustValue":null,"armor":null,"background":"他整天与战马为伍，终年无休。","cardSet":"core","craftingCost":null,"cardId":69703,"availableGameModes":["constructed","duels"],"name":"战马训练师","parentCard":null,"ids":null,"legacyKeywords":"随从,普通,核心,圣骑士","code":"69703-warhorse-trainer","artist":"Zoltan & Gabor","description":"你的白银之手新兵获得+1攻击力。","consume":0,"cropImage":"https://hearthstone.nosdn.127.net/hearthstone/f5ffc64bb2faf44fb89bba5f3d0303a1ca9a1467852eb047e30bc1a13fa141d2.png","gain":0,"classId":5,"cardEffect":"","tier":null,"attack":3,"imageUrl":"https://hearthstone.nosdn.127.net/hearthstone/f5991ac16ea1c95ed31820996b3b5799e090ef0f8f849c1919b5197817cc4a92.png","cardRarity":"common","cardSetId":1637,"minionTypeId":null,"cost":3,"cardCode":"","cardType":"minion","standardCard":true,"health":4,"updateTime":null,"classicCard":false,"parentId":null,"cardMultiClass":[],"createTime":null,"minionType":null,"imageGold":"","artistName":"Zoltan & Gabor","availableClassIds":[5],"manaCost":3,"wildCard":true},{"cardRace":"common","standard":0,"flavorText":"他整天与战马为伍，终年无休。","collectible":1,"keywords":[],"battlegrounds":null,"keywordIds":null,"pic":"https://hearthstone.nosdn.127.net/hearthstone/5fed8a6a9d0656c4f7e099364f6d2ee141eec0c7e9e821e8c13a9beb806dd8fe.png","spellSchoolId":null,"childCards":null,"childIds":null,"multiClassIds":[],"golden":0,"id":2515,"cardTypeId":4,"text":"你的白银之手新兵获得+1攻击力。","cardClass":"paladin","slug":"2515-warhorse-trainer","image":"https://hearthstone.nosdn.127.net/hearthstone/5fed8a6a9d0656c4f7e099364f6d2ee141eec0c7e9e821e8c13a9beb806dd8fe.png","neutralClass":null,"durability":null,"rarityId":1,"dustValue":null,"armor":null,"background":"他整天与战马为伍，终年无休。","cardSet":"tgt","craftingCost":null,"cardId":2515,"availableGameModes":["constructed"],"name":"战马训练师","parentCard":null,"ids":null,"legacyKeywords":"随从,普通,冠军的试炼,圣骑士","code":"2515-warhorse-trainer","artist":"Zoltan & Gabor","description":"你的白银之手新兵获得+1攻击力。","consume":0,"cropImage":"https://hearthstone.nosdn.127.net/hearthstone/f5ffc64bb2faf44fb89bba5f3d0303a1ca9a1467852eb047e30bc1a13fa141d2.png","gain":0,"classId":5,"cardEffect":"","tier":null,"attack":3,"imageUrl":"https://hearthstone.nosdn.127.net/hearthstone/5fed8a6a9d0656c4f7e099364f6d2ee141eec0c7e9e821e8c13a9beb806dd8fe.png","cardRarity":"common","cardSetId":15,"minionTypeId":null,"cost":3,"cardCode":"","cardType":"minion","standardCard":false,"health":4,"updateTime":null,"classicCard":false,"parentId":null,"cardMultiClass":[],"createTime":null,"minionType":null,"imageGold":"","artistName":"Zoltan & Gabor","availableClassIds":[5],"manaCost":3,"wildCard":true},{"cardRace":"legendary","standard":0,"flavorText":"两个人也是可以保守秘密的，除非其中一个是蕾撒。","collectible":1,"keywords":["secret"],"battlegrounds":null,"keywordIds":[5],"pic":"https://hearthstone.nosdn.127.net/hearthstone/f3a296ea780fef78dc968d92ccdf7b8b19f339d67b6ed8ebc71678e4a439e092.png","spellSchoolId":null,"childCards":null,"childIds":null,"multiClassIds":[],"golden":0,"id":52500,"cardTypeId":4,"text":"你的<b>奥秘</b>会触发 两次。","cardClass":"paladin","slug":"52500-commander-rhyssa","image":"https://hearthstone.nosdn.127.net/hearthstone/f3a296ea780fef78dc968d92ccdf7b8b19f339d67b6ed8ebc71678e4a439e092.png","neutralClass":null,"durability":null,"rarityId":5,"dustValue":null,"armor":null,"background":"两个人也是可以保守秘密的，除非其中一个是蕾撒。","cardSet":"rise-of-shadows","craftingCost":null,"cardId":52500,"availableGameModes":["constructed","arena"],"name":"指挥官蕾撒","parentCard":null,"ids":null,"legacyKeywords":"随从,传说,暗影崛起,圣骑士,奥秘","code":"52500-commander-rhyssa","artist":"Luke Mancini","description":"你的<b>奥秘</b>会触发 两次。","consume":0,"cropImage":"https://hearthstone.nosdn.127.net/hearthstone/936c9a0c64115ae8b3b3a3206673c13e54905a24cf9e0edac01be79281ed9242.png","gain":0,"classId":5,"cardEffect":"secret","tier":null,"attack":4,"imageUrl":"https://hearthstone.nosdn.127.net/hearthstone/f3a296ea780fef78dc968d92ccdf7b8b19f339d67b6ed8ebc71678e4a439e092.png","cardRarity":"legendary","cardSetId":1130,"minionTypeId":null,"cost":3,"cardCode":"","cardType":"minion","standardCard":false,"health":3,"updateTime":null,"classicCard":false,"parentId":null,"cardMultiClass":[],"createTime":null,"minionType":null,"imageGold":"","artistName":"Luke Mancini","availableClassIds":[5],"manaCost":3,"wildCard":true},{"cardRace":"common","standard":0,"flavorText":"这就是……圣骑士的绝对领域吗？！","collectible":1,"keywords":["immune"],"battlegrounds":null,"keywordIds":[17],"pic":"https://hearthstone.nosdn.127.net/hearthstone/a81fd9c2c5db2fa3e3431b6d2a61d5e1cac42eb0719cde6033764aefe3156ae4.png","spellSchoolId":null,"childCards":null,"childIds":null,"multiClassIds":[],"golden":0,"id":49999,"cardTypeId":5,"text":"直到你的下个回合，你的英雄获得<b>免疫</b>。","cardClass":"paladin","slug":"49999-time-out","image":"https://hearthstone.nosdn.127.net/hearthstone/a81fd9c2c5db2fa3e3431b6d2a61d5e1cac42eb0719cde6033764aefe3156ae4.png","neutralClass":null,"durability":null,"rarityId":1,"dustValue":null,"armor":null,"background":"这就是……圣骑士的绝对领域吗？！","cardSet":"rastakhans-rumble","craftingCost":null,"cardId":49999,"availableGameModes":["constructed"],"name":"暂避锋芒","parentCard":null,"ids":null,"legacyKeywords":"法术,普通,大乱斗,圣骑士,免疫","code":"49999-time-out","artist":"Arthur Bozonnet","description":"直到你的下个回合，你的英雄获得<b>免疫</b>。","consume":0,"cropImage":"https://hearthstone.nosdn.127.net/hearthstone/534d61d4003a0e45651ab8caf3c9ecd1e61d2022d4105fecac490c99f451d235.png","gain":0,"classId":5,"cardEffect":"immune","tier":null,"attack":null,"imageUrl":"https://hearthstone.nosdn.127.net/hearthstone/a81fd9c2c5db2fa3e3431b6d2a61d5e1cac42eb0719cde6033764aefe3156ae4.png","cardRarity":"common","cardSetId":1129,"minionTypeId":null,"cost":3,"cardCode":"","cardType":"spell","standardCard":false,"health":null,"updateTime":null,"classicCard":false,"parentId":null,"cardMultiClass":[],"createTime":null,"minionType":null,"imageGold":"https://hearthstone.nosdn.127.net/hearthstone/1da2079068847f53471546e92db4f91dcb806e4429493517594568dd0723b32d.png","artistName":"Arthur Bozonnet","availableClassIds":[5],"manaCost":3,"wildCard":true},{"cardRace":"rare","standard":0,"flavorText":"手里拿着一把未鉴定的槌子，看什么就都像未鉴定的钉子。","collectible":1,"keywords":[],"battlegrounds":null,"keywordIds":null,"pic":"https://hearthstone.nosdn.127.net/hearthstone/6f433f0e3a96a87226691dd8a500a0a006eda6ab96b105b291d75dd3fbfe7d43.png","spellSchoolId":null,"childCards":[{"flavorText":"","collectible":0,"battlegrounds":null,"keywordIds":null,"spellSchoolId":null,"cropImage":"https://hearthstone.nosdn.127.net/hearthstone/8a60b28b4a9bb70748ce68815582bbde7a0c2ebfdf70988adb51da88c5d655fc.jpg","classId":5,"tier":null,"childIds":null,"attack":1,"multiClassIds":[],"cardSetId":1635,"cardTypeId":4,"id":1652,"text":"","minionTypeId":null,"slug":"1652-silver-hand-recruit","image":"https://hearthstone.nosdn.127.net/hearthstone/e3039c3202328aa9484d6279c1a9a924d4fc96c811c700d183c4370c67feb7b2.png","durability":null,"health":1,"parentId":null,"rarityId":2,"armor":null,"availableGameModes":["constructed"],"name":"白银之手新兵","imageGold":"","artistName":null,"availableClassIds":[5],"manaCost":1},{"flavorText":"","collectible":0,"battlegrounds":null,"keywordIds":[8],"spellSchoolId":null,"cropImage":null,"classId":5,"tier":null,"childIds":null,"attack":2,"multiClassIds":[],"cardSetId":1004,"cardTypeId":7,"id":45777,"text":"<b>战吼：</b>使你的所有随从获得<b>嘲讽</b>。","minionTypeId":null,"slug":"45777-sacred-maul","image":"https://hearthstone.nosdn.127.net/hearthstone/95a7bb8ba008dcd2c3aaa4655d2ee6848741a98af4f704cb245c61908e44a248.png","durability":2,"health":null,"parentId":null,"rarityId":3,"armor":null,"availableGameModes":["constructed"],"name":"神圣重槌","imageGold":"","artistName":"Konstantin Turovec","availableClassIds":[5],"manaCost":3},{"flavorText":"","collectible":0,"battlegrounds":null,"keywordIds":[8],"spellSchoolId":null,"cropImage":null,"classId":5,"tier":null,"childIds":null,"attack":2,"multiClassIds":[],"cardSetId":1004,"cardTypeId":7,"id":45778,"text":"<b>战吼：</b>使你的所有随从获得+1 攻击力。","minionTypeId":null,"slug":"45778-blessed-maul","image":"https://hearthstone.nosdn.127.net/hearthstone/3fa3a67bf2df5e6ebab32d550a264ef3c62e950d022f91029cb4daa3a06abc1f.png","durability":2,"health":null,"parentId":null,"rarityId":3,"armor":null,"availableGameModes":["constructed"],"name":"祝福重槌","imageGold":"","artistName":"Konstantin Turovec","availableClassIds":[5],"manaCost":3},{"flavorText":"","collectible":0,"battlegrounds":null,"keywordIds":[8],"spellSchoolId":null,"cropImage":null,"classId":5,"tier":null,"childIds":[1652],"attack":2,"multiClassIds":[],"cardSetId":1004,"cardTypeId":7,"id":45779,"text":"<b>战吼：</b>召唤两个1/1的白银之手新兵。","minionTypeId":null,"slug":"45779-champions-maul","image":"https://hearthstone.nosdn.127.net/hearthstone/c9b0b5deb3506a36022d90e9fa156b65442b1258fc239fae9ad2b77fba5c0cce.png","durability":2,"health":null,"parentId":null,"rarityId":3,"armor":null,"availableGameModes":["constructed"],"name":"勇士重槌","imageGold":"","artistName":"Konstantin Turovec","availableClassIds":[5],"manaCost":3},{"flavorText":"","collectible":0,"battlegrounds":null,"keywordIds":[8],"spellSchoolId":null,"cropImage":null,"classId":5,"tier":null,"childIds":null,"attack":2,"multiClassIds":[],"cardSetId":1004,"cardTypeId":7,"id":45780,"text":"<b>战吼：</b>使你的所有随从获得<b>圣盾</b>。","minionTypeId":null,"slug":"45780-purifiers-maul","image":"https://hearthstone.nosdn.127.net/hearthstone/0a3c76480e413d258d4c6093f41ea99de9184de71900366e57898fff602b6b3d.png","durability":2,"health":null,"parentId":null,"rarityId":3,"armor":null,"availableGameModes":["constructed"],"name":"净化重槌","imageGold":"","artistName":"Konstantin Turovec","availableClassIds":[5],"manaCost":3}],"childIds":[1652,45777,45778,45779,45780],"multiClassIds":[],"golden":0,"id":45782,"cardTypeId":7,"text":"在你手牌中时获得额外效果。","cardClass":"paladin","slug":"45782-unidentified-maul","image":"https://hearthstone.nosdn.127.net/hearthstone/6f433f0e3a96a87226691dd8a500a0a006eda6ab96b105b291d75dd3fbfe7d43.png","neutralClass":null,"durability":2,"rarityId":3,"dustValue":null,"armor":null,"background":"手里拿着一把未鉴定的槌子，看什么就都像未鉴定的钉子。","cardSet":"kobolds-catacombs","craftingCost":null,"cardId":45782,"availableGameModes":["constructed"],"name":"未鉴定的重槌","parentCard":null,"ids":null,"legacyKeywords":"武器,稀有,狗头人,圣骑士","code":"45782-unidentified-maul","artist":"Dan Scott","description":"在你手牌中时获得额外效果。","consume":0,"cropImage":"https://hearthstone.nosdn.127.net/hearthstone/9d1bd21f13aec645b2c34a6186c5fc5e619b478fce7f9c16d1ae81422e283a25.jpg","gain":0,"classId":5,"cardEffect":"","tier":null,"attack":2,"imageUrl":"https://hearthstone.nosdn.127.net/hearthstone/6f433f0e3a96a87226691dd8a500a0a006eda6ab96b105b291d75dd3fbfe7d43.png","cardRarity":"rare","cardSetId":1004,"minionTypeId":null,"cost":3,"cardCode":"","cardType":"weapon","standardCard":false,"health":null,"updateTime":null,"classicCard":false,"parentId":null,"cardMultiClass":[],"createTime":null,"minionType":null,"imageGold":"","artistName":"Dan Scott","availableClassIds":[5],"manaCost":3,"wildCard":true},{"cardRace":"common","standard":0,"flavorText":"无论你想要什么，她都能给你弄来！","collectible":1,"keywords":["battlecry"],"battlegrounds":null,"keywordIds":[8,27],"pic":"https://hearthstone.nosdn.127.net/hearthstone/0e334323869fd58284fb507c6b3479a26b66511e183b69c77994de8be2147612.png","spellSchoolId":null,"childCards":null,"childIds":null,"multiClassIds":[3,5,10],"golden":0,"id":40743,"cardTypeId":4,"text":"<b>战吼：</b>随机使你手牌中的一张随从牌获得+1/+1。","cardClass":"","slug":"40743-grimestreet-smuggler","image":"https://hearthstone.nosdn.127.net/hearthstone/0e334323869fd58284fb507c6b3479a26b66511e183b69c77994de8be2147612.png","neutralClass":null,"durability":null,"rarityId":1,"dustValue":null,"armor":null,"background":"无论你想要什么，她都能给你弄来！","cardSet":"msog","craftingCost":null,"cardId":40743,"availableGameModes":["constructed"],"name":"污手街走私者","parentCard":null,"ids":null,"legacyKeywords":"随从,普通,加基森,中立,猎人,圣骑士,战士,战吼","code":"40743-grimestreet-smuggler","artist":"Sean McNally","description":"<b>战吼：</b>随机使你手牌中的一张随从牌获得+1/+1。","consume":0,"cropImage":"https://hearthstone.nosdn.127.net/hearthstone/01d752c81f7ce720530d3ec948e4480e6725b94b1c945698d6f04a09a9ad57a4.png","gain":0,"classId":12,"cardEffect":"battlecry","tier":null,"attack":2,"imageUrl":"https://hearthstone.nosdn.127.net/hearthstone/0e334323869fd58284fb507c6b3479a26b66511e183b69c77994de8be2147612.png","cardRarity":"common","cardSetId":25,"minionTypeId":null,"cost":3,"cardCode":"","cardType":"minion","standardCard":false,"health":4,"updateTime":null,"classicCard":false,"parentId":null,"cardMultiClass":["hunter","paladin","warrior"],"createTime":null,"minionType":null,"imageGold":"https://hearthstone.nosdn.127.net/hearthstone/ccee557a24f464597dadf1878af383a2f906902e15433efa5ed34b7f3f57c45d.png","artistName":"Sean McNally","availableClassIds":[3,5,10],"manaCost":3,"wildCard":true},{"cardRace":"rare","standard":1,"flavorText":"圣光会赐给你一份小纪念品，一个小雪花球，里面装着微缩版的你。","collectible":1,"keywords":["divine-shield"],"battlegrounds":null,"keywordIds":[3],"pic":"https://hearthstone.nosdn.127.net/hearthstone/dc51b27b9c87d304d034ce04bcaaceff112701bdbb655e65f1fca50bd444148b.png","spellSchoolId":5,"childCards":null,"childIds":null,"multiClassIds":[5,6],"golden":0,"id":58791,"cardTypeId":5,"text":"使一个随从获得<b>圣盾</b>，并召唤一个1/1的复制。","cardClass":"","slug":"58791-gift-of-luminance","image":"https://hearthstone.nosdn.127.net/hearthstone/dc51b27b9c87d304d034ce04bcaaceff112701bdbb655e65f1fca50bd444148b.png","neutralClass":null,"durability":null,"rarityId":3,"dustValue":null,"armor":null,"background":"圣光会赐给你一份小纪念品，一个小雪花球，里面装着微缩版的你。","cardSet":"scholomance-academy","craftingCost":null,"cardId":58791,"availableGameModes":["constructed","duels"],"name":"流光之赐","parentCard":null,"ids":null,"legacyKeywords":"法术,稀有,通灵学园,圣骑士,牧师,圣盾","code":"58791-gift-of-luminance","artist":"L. Lullabi & K. Turovec","description":"使一个随从获得<b>圣盾</b>，并召唤一个1/1的复制。","consume":0,"cropImage":"https://hearthstone.nosdn.127.net/hearthstone/e6de7ad584f5d49e56621a8872912968f4d9933f824f0695165289a34a8f2aec.png","gain":0,"classId":5,"cardEffect":"divine-shield","tier":null,"attack":null,"imageUrl":"https://hearthstone.nosdn.127.net/hearthstone/dc51b27b9c87d304d034ce04bcaaceff112701bdbb655e65f1fca50bd444148b.png","cardRarity":"rare","cardSetId":1443,"minionTypeId":null,"cost":3,"cardCode":"","cardType":"spell","standardCard":true,"health":null,"updateTime":null,"classicCard":false,"parentId":null,"cardMultiClass":["paladin","priest"],"createTime":null,"minionType":null,"imageGold":"","artistName":"L. Lullabi & K. Turovec","availableClassIds":[5,6],"manaCost":3,"wildCard":true}],"curPage":14,"prePage":13,"nextPage":15,"totalPage":29,"totalPerClass":{"demonhunter":109,"hunter":230,"druid":230,"shaman":230,"paladin":230,"warrior":230,"rogue":232,"mage":231,"priest":237,"warlock":232,"neutral":1048},"pageSize":8,"curCardClass":"paladin"}