{"total":230,"cards":[{"cardRace":"epic","standard":0,"flavorText":"“温德，灯再亮一点！”“我已经开到最大啦，坎格尔！”","collectible":1,"keywords":["battlecry"],"battlegrounds":null,"keywordIds":[8],"pic":"https://hearthstone.nosdn.127.net/hearthstone/5b23a1ab69ce31a53452a8be5f92684974aa47e6ce573670919bcb9e61fb81ef.png","spellSchoolId":null,"childCards":null,"childIds":null,"multiClassIds":[],"golden":0,"id":48989,"cardTypeId":4,"text":"<b>战吼：</b>使你手牌中的所有随从牌获得+2/+2。","cardClass":"paladin","slug":"48989-glowstone-technician","image":"https://hearthstone.nosdn.127.net/hearthstone/5b23a1ab69ce31a53452a8be5f92684974aa47e6ce573670919bcb9e61fb81ef.png","neutralClass":null,"durability":null,"rarityId":4,"dustValue":null,"armor":null,"background":"“温德，灯再亮一点！”“我已经开到最大啦，坎格尔！”","cardSet":"boomsday-project","craftingCost":null,"cardId":48989,"availableGameModes":["constructed"],"name":"亮石技师","parentCard":null,"ids":null,"legacyKeywords":"随从,史诗,砰砰计划,圣骑士,战吼","code":"48989-glowstone-technician","artist":"Anton Zemskov","description":"<b>战吼：</b>使你手牌中的所有随从牌获得+2/+2。","consume":0,"cropImage":"https://hearthstone.nosdn.127.net/hearthstone/5e665bd6d89ff42f757b4f661fd5509be1d8d3ef69529459e1b2554e6caac367.png","gain":0,"classId":5,"cardEffect":"battlecry","tier":null,"attack":3,"imageUrl":"https://hearthstone.nosdn.127.net/hearthstone/5b23a1ab69ce31a53452a8be5f92684974aa47e6ce573670919bcb9e61fb81ef.png","cardRarity":"epic","cardSetId":1127,"minionTypeId":null,"cost":5,"cardCode":"","cardType":"minion","standardCard":false,"health":4,"updateTime":null,"classicCard":false,"parentId":null,"cardMultiClass":[],"createTime":null,"minionType":null,"imageGold":"https://hearthstone.nosdn.127.net/hearthstone/6b59f04492833b0374d7d5c29f8dfa056351fb29fda90c92e4f417e50e716549.png","artistName":"Anton Zemskov","availableClassIds":[5],"manaCost":5,"wildCard":true},{"cardRace":"legendary","standard":0,"flavorText":"在伯瓦尔身上的冰融化之后，他受邀接受了采访。在采访中他对艾泽拉斯全球气候变暖现象表达了深深的忧虑。","collectible":1,"keywords":[],"battlegrounds":null,"keywordIds":null,"pic":"https://hearthstone.nosdn.127.net/hearthstone/8923a44873b679232cc1963e003aba6d778724ffd20685adc6cfa83446801374.png","spellSchoolId":null,"childCards":null,"childIds":null,"multiClassIds":[],"golden":0,"id":2031,"cardTypeId":4,"text":"如果这张牌在你的手牌中，每当一个友方随从死亡，便获得+1攻击力。","cardClass":"paladin","slug":"2031-bolvar-fordragon","image":"https://hearthstone.nosdn.127.net/hearthstone/8923a44873b679232cc1963e003aba6d778724ffd20685adc6cfa83446801374.png","neutralClass":null,"durability":null,"rarityId":5,"dustValue":null,"armor":null,"background":"在伯瓦尔身上的冰融化之后，他受邀接受了采访。在采访中他对艾泽拉斯全球气候变暖现象表达了深深的忧虑。","cardSet":"gvg","craftingCost":null,"cardId":2031,"availableGameModes":["constructed"],"name":"伯瓦尔·弗塔根","parentCard":null,"ids":null,"legacyKeywords":"随从,传说,地精大战侏儒,圣骑士","code":"2031-bolvar-fordragon","artist":"Tooth","description":"如果这张牌在你的手牌中，每当一个友方随从死亡，便获得+1攻击力。","consume":0,"cropImage":"https://hearthstone.nosdn.127.net/hearthstone/f5d5eb8c785b07bfd5ed7c826192b8e026b06fadec87abfb44f99334a77715dc.jpg","gain":0,"classId":5,"cardEffect":"","tier":null,"attack":1,"imageUrl":"https://hearthstone.nosdn.127.net/hearthstone/8923a44873b679232cc1963e003aba6d778724ffd20685adc6cfa83446801374.png","cardRarity":"legendary","cardSetId":13,"minionTypeId":null,"cost":5,"cardCode":"","cardType":"minion","standardCard":false,"health":7,"updateTime":null,"classicCard":false,"parentId":null,"cardMultiClass":[],"createTime":null,"minionType":null,"imageGold":"","artistName":"Tooth","availableClassIds":[5],"manaCost":5,"wildCard":true},{"cardRace":"epic","standard":0,"flavorText":"自从乌瑟尔把他招募到麾下之后，他觉得新兵大喊“报告”的声音不再那么烦人了。","collectible":1,"keywords":["battlecry"],"battlegrounds":null,"keywordIds":[8],"pic":"https://hearthstone.nosdn.127.net/hearthstone/f17d85edddc9d611c5d90550f9bd69b9ab6a90156d300a15da050b0589e3f173.png","spellSchoolId":null,"childCards":null,"childIds":null,"multiClassIds":[],"golden":0,"id":2028,"cardTypeId":4,"text":"<b>战吼：</b>使你的白银之手新兵获得+2/+2。","cardClass":"paladin","slug":"2028-quartermaster","image":"https://hearthstone.nosdn.127.net/hearthstone/f17d85edddc9d611c5d90550f9bd69b9ab6a90156d300a15da050b0589e3f173.png","neutralClass":null,"durability":null,"rarityId":4,"dustValue":null,"armor":null,"background":"自从乌瑟尔把他招募到麾下之后，他觉得新兵大喊“报告”的声音不再那么烦人了。","cardSet":"gvg","craftingCost":null,"cardId":2028,"availableGameModes":["constructed"],"name":"军需官","parentCard":null,"ids":null,"legacyKeywords":"随从,史诗,地精大战侏儒,圣骑士,战吼","code":"2028-quartermaster","artist":"Phroilan Gardner","description":"<b>战吼：</b>使你的白银之手新兵获得+2/+2。","consume":0,"cropImage":"https://hearthstone.nosdn.127.net/hearthstone/765558c2773e15cc171ec993a499398a8767529db9dd5017912bc3133e6d95e1.jpg","gain":0,"classId":5,"cardEffect":"battlecry","tier":null,"attack":2,"imageUrl":"https://hearthstone.nosdn.127.net/hearthstone/f17d85edddc9d611c5d90550f9bd69b9ab6a90156d300a15da050b0589e3f173.png","cardRarity":"epic","cardSetId":13,"minionTypeId":null,"cost":5,"cardCode":"","cardType":"minion","standardCard":false,"health":5,"updateTime":null,"classicCard":false,"parentId":null,"cardMultiClass":[],"createTime":null,"minionType":null,"imageGold":"","artistName":"Phroilan Gardner","availableClassIds":[5],"manaCost":5,"wildCard":true},{"cardRace":"epic","standard":0,"flavorText":"我要中单，不给就送。","collectible":1,"keywords":[],"battlegrounds":null,"keywordIds":null,"pic":"https://hearthstone.nosdn.127.net/hearthstone/204da6c14eb88742a0a5affaf3aa5c21d55d05bacc29eb456c117da8e3eb8b61.png","spellSchoolId":null,"childCards":null,"childIds":null,"multiClassIds":[],"golden":0,"id":52742,"cardTypeId":5,"text":"从双方玩家的牌库中各召唤一个随从，并使其互相 攻击！","cardClass":"paladin","slug":"52742-duel","image":"https://hearthstone.nosdn.127.net/hearthstone/204da6c14eb88742a0a5affaf3aa5c21d55d05bacc29eb456c117da8e3eb8b61.png","neutralClass":null,"durability":null,"rarityId":4,"dustValue":null,"armor":null,"background":"我要中单，不给就送。","cardSet":"rise-of-shadows","craftingCost":null,"cardId":52742,"availableGameModes":["constructed","arena"],"name":"决斗","parentCard":null,"ids":null,"legacyKeywords":"法术,史诗,暗影崛起,圣骑士","code":"52742-duel","artist":"Konstantin Turovec","description":"从双方玩家的牌库中各召唤一个随从，并使其互相 攻击！","consume":0,"cropImage":"https://hearthstone.nosdn.127.net/hearthstone/12e599f9d493a4346f637213b9c696d2c4203ca4871bab3e4389729b894a736a.png","gain":0,"classId":5,"cardEffect":"","tier":null,"attack":null,"imageUrl":"https://hearthstone.nosdn.127.net/hearthstone/204da6c14eb88742a0a5affaf3aa5c21d55d05bacc29eb456c117da8e3eb8b61.png","cardRarity":"epic","cardSetId":1130,"minionTypeId":null,"cost":5,"cardCode":"","cardType":"spell","standardCard":false,"health":null,"updateTime":null,"classicCard":false,"parentId":null,"cardMultiClass":[],"createTime":null,"minionType":null,"imageGold":"","artistName":"Konstantin Turovec","availableClassIds":[5],"manaCost":5,"wildCard":true},{"cardRace":"legendary","standard":0,"flavorText":"“我有一项非常特殊的能力，这能力会让我成为女巫的噩梦。”","collectible":1,"keywords":["battlecry"],"battlegrounds":null,"keywordIds":[8],"pic":"https://hearthstone.nosdn.127.net/hearthstone/4bea84d44c92a905aebb86e4762bf594f180d9840955a085a43617e58fe1415e.png","spellSchoolId":null,"childCards":null,"childIds":null,"multiClassIds":[],"golden":0,"id":47696,"cardTypeId":4,"text":"<b>战吼：</b>将你牌库中所有法力值消耗为（1）的牌变为<b>传说</b>随从牌。","cardClass":"paladin","slug":"47696-prince-liam","image":"https://hearthstone.nosdn.127.net/hearthstone/4bea84d44c92a905aebb86e4762bf594f180d9840955a085a43617e58fe1415e.png","neutralClass":null,"durability":null,"rarityId":5,"dustValue":null,"armor":null,"background":"“我有一项非常特殊的能力，这能力会让我成为女巫的噩梦。”","cardSet":"the-witchwood","craftingCost":null,"cardId":47696,"availableGameModes":["constructed"],"name":"利亚姆王子","parentCard":null,"ids":null,"legacyKeywords":"随从,传说,女巫森林,圣骑士,战吼","code":"47696-prince-liam","artist":"James Ryman","description":"<b>战吼：</b>将你牌库中所有法力值消耗为（1）的牌变为<b>传说</b>随从牌。","consume":0,"cropImage":"https://hearthstone.nosdn.127.net/hearthstone/664e042caf97959d80c05dd31063c5e9bca7964177e225ef0c61aa1cbda86550.png","gain":0,"classId":5,"cardEffect":"battlecry","tier":null,"attack":5,"imageUrl":"https://hearthstone.nosdn.127.net/hearthstone/4bea84d44c92a905aebb86e4762bf594f180d9840955a085a43617e58fe1415e.png","cardRarity":"legendary","cardSetId":1125,"minionTypeId":null,"cost":5,"cardCode":"","cardType":"minion","standardCard":false,"health":5,"updateTime":null,"classicCard":false,"parentId":null,"cardMultiClass":[],"createTime":null,"minionType":null,"imageGold":"https://hearthstone.nosdn.127.net/hearthstone/6b5985a792c5db0ee749d26bf4b928f4826551467d34d88ae4ac3f8d107d9cc3.png","artistName":"James Ryman","availableClassIds":[5],"manaCost":5,"wildCard":true},{"cardRace":"rare","standard":0,"flavorText":"“攻击翻倍，快乐加倍！”","collectible":1,"keywords":[],"battlegrounds":null,"keywordIds":null,"pic":"https://hearthstone.nosdn.127.net/hearthstone/25f9fa33b22017581f612b0e9637c93338a09a0db616b805ff1446828db8e6b6.png","spellSchoolId":5,"childCards":null,"childIds":null,"multiClassIds":[],"golden":0,"id":1522,"cardTypeId":5,"text":"使一个随从的攻击力翻倍。","cardClass":"paladin","slug":"1522-blessed-champion","image":"https://hearthstone.nosdn.127.net/hearthstone/25f9fa33b22017581f612b0e9637c93338a09a0db616b805ff1446828db8e6b6.png","neutralClass":null,"durability":null,"rarityId":3,"dustValue":null,"armor":null,"background":"“攻击翻倍，快乐加倍！”","cardSet":"legacy","craftingCost":null,"cardId":1522,"availableGameModes":["constructed","arena","duels"],"name":"受祝福的勇士","parentCard":null,"ids":null,"legacyKeywords":"法术,稀有,圣骑士","code":"1522-blessed-champion","artist":"Tyler Walpole","description":"使一个随从的攻击力翻倍。","consume":0,"cropImage":"https://hearthstone.nosdn.127.net/hearthstone/4414b5c913b0bce6063f115ff7d423f520259df2df350bc187672b944800c34e.png","gain":0,"classId":5,"cardEffect":"","tier":null,"attack":null,"imageUrl":"https://hearthstone.nosdn.127.net/hearthstone/25f9fa33b22017581f612b0e9637c93338a09a0db616b805ff1446828db8e6b6.png","cardRarity":"rare","cardSetId":3,"minionTypeId":null,"cost":5,"cardCode":"","cardType":"spell","standardCard":false,"health":null,"updateTime":null,"classicCard":false,"parentId":null,"cardMultiClass":[],"createTime":null,"minionType":null,"imageGold":"https://hearthstone.nosdn.127.net/hearthstone/2b71a8be8bbf95cfcd28c6974f1f308eebf0227aef9aa41f656e6cebd1f7410a.png","artistName":"Tyler Walpole","availableClassIds":[5],"manaCost":5,"wildCard":true},{"cardRace":"rare","standard":1,"flavorText":"真理在圣契范围之内。","collectible":1,"keywords":["taunt","battlecry"],"battlegrounds":null,"keywordIds":[1,8],"pic":"https://hearthstone.nosdn.127.net/hearthstone/7b6671bdae31cbf3c6edb7a32bf96b7cd4d66a56a831cf2f548131bfc8ea633c.png","spellSchoolId":null,"childCards":[{"flavorText":"对方不想说话并向你扔了一本书。","collectible":1,"battlegrounds":null,"keywordIds":null,"spellSchoolId":5,"cropImage":"https://hearthstone.nosdn.127.net/hearthstone/dd7ddb48772fe97d89fb0520fd31363b54ee1e53e5f5bf8724440a8909777780.png","classId":5,"tier":null,"childIds":[57738],"attack":null,"multiClassIds":[],"cardSetId":1414,"cardTypeId":5,"id":56394,"text":"装备一把1/4的武器。将所有敌方随从的生命值变为1。","minionTypeId":null,"slug":"56394-libram-of-justice","image":"https://hearthstone.nosdn.127.net/hearthstone/87fd13e68d7f23cb85f2c00b3eed2233296fab39cef221b3714acde4ee7ef5e5.png","durability":null,"health":null,"parentId":null,"rarityId":1,"armor":null,"availableGameModes":["constructed","arena"],"name":"正义圣契","imageGold":"","artistName":"Wayne Wu","availableClassIds":[5],"manaCost":5},{"flavorText":"感谢这些白衣勇士。守卫生命，守卫希望。","collectible":1,"battlegrounds":null,"keywordIds":[1,3],"spellSchoolId":5,"cropImage":"https://hearthstone.nosdn.127.net/hearthstone/d38a29ebff4fbbd74c262b8db9cdb04b7fba153637628236a86120eb55f02d22.png","classId":5,"tier":null,"childIds":[57471],"attack":null,"multiClassIds":[],"cardSetId":1414,"cardTypeId":5,"id":56554,"text":"恢复8点生命值。召唤一个8/8并具有<b>嘲讽</b>和<b>圣盾</b>的 守卫。","minionTypeId":null,"slug":"56554-libram-of-hope","image":"https://hearthstone.nosdn.127.net/hearthstone/6ae31afe9cdea33d3e4f15eecc049fd6a3e93a96c4b1ae32380ef5b9f7e0da99.png","durability":null,"health":null,"parentId":null,"rarityId":4,"armor":null,"availableGameModes":["constructed","arena"],"name":"希望圣契","imageGold":"","artistName":"MAR Studio","availableClassIds":[5],"manaCost":9},{"flavorText":"最好的智慧便是传承。","collectible":1,"battlegrounds":null,"keywordIds":[12],"spellSchoolId":5,"cropImage":"https://hearthstone.nosdn.127.net/hearthstone/ab061ea3d7bb96a6d345aa49f5ddfd0e8131d7e3eba5d5632cc8ae98f59fe9d1.png","classId":5,"tier":null,"childIds":null,"attack":null,"multiClassIds":[],"cardSetId":1414,"cardTypeId":5,"id":56555,"text":"使一个随从获得+1/+1，以及“<b>亡语：</b>将一张‘智慧圣契’法术牌置入你的手牌。”","minionTypeId":null,"slug":"56555-libram-of-wisdom","image":"https://hearthstone.nosdn.127.net/hearthstone/85260b2b80f90cecb2cbd481a31c7b41370b17305baf323be418c0e8153c8633.png","durability":null,"health":null,"parentId":null,"rarityId":3,"armor":null,"availableGameModes":["constructed","arena"],"name":"智慧圣契","imageGold":"","artistName":"Adam Byrne","availableClassIds":[5],"manaCost":2},{"flavorText":"","collectible":0,"battlegrounds":null,"keywordIds":[1,3],"spellSchoolId":null,"cropImage":"https://hearthstone.nosdn.127.net/hearthstone/701837bf4ac1623a513d166f1cefb7e93a4b24522a1844ef4cdb93ca3932f08d.jpg","classId":5,"tier":null,"childIds":null,"attack":8,"multiClassIds":[],"cardSetId":1414,"cardTypeId":4,"id":57471,"text":"<b>嘲讽，圣盾</b>","minionTypeId":null,"slug":"57471-ancient-guardian","image":"https://hearthstone.nosdn.127.net/hearthstone/d594f29f37b01a803d712a82d386eb8b11c738db1c01e585044088756b50ffd0.png","durability":null,"health":8,"parentId":56554,"rarityId":null,"armor":null,"availableGameModes":["constructed"],"name":"远古守卫","imageGold":"","artistName":"MAR Studio","availableClassIds":[5],"manaCost":8},{"flavorText":"","collectible":0,"battlegrounds":null,"keywordIds":null,"spellSchoolId":null,"cropImage":"https://hearthstone.nosdn.127.net/hearthstone/63bf75d88f621e38a10d26ad0cb147252d8a7aba1061fbf41b2f879954956589.jpg","classId":5,"tier":null,"childIds":null,"attack":1,"multiClassIds":[],"cardSetId":1414,"cardTypeId":7,"id":57738,"text":"","minionTypeId":null,"slug":"57738-overdue-justice","image":"https://hearthstone.nosdn.127.net/hearthstone/be26a47bfd327e062682bc685c23d72d962e4012125721701c656fe3555d751c.png","durability":4,"health":null,"parentId":56394,"rarityId":null,"armor":null,"availableGameModes":["constructed"],"name":"迟到的正义","imageGold":"","artistName":"Wayne Wu","availableClassIds":[5],"manaCost":1}],"childIds":[56394,56554,56555,57471,57738],"multiClassIds":[],"golden":0,"id":56556,"cardTypeId":4,"text":"<b>嘲讽，战吼：</b> 在本局对战中，你的圣契的法力值消耗减少（2）点。","cardClass":"paladin","slug":"56556-aldor-truthseeker","image":"https://hearthstone.nosdn.127.net/hearthstone/7b6671bdae31cbf3c6edb7a32bf96b7cd4d66a56a831cf2f548131bfc8ea633c.png","neutralClass":null,"durability":null,"rarityId":3,"dustValue":null,"armor":null,"background":"真理在圣契范围之内。","cardSet":"ashes-of-outland","craftingCost":null,"cardId":56556,"availableGameModes":["constructed","arena"],"name":"奥尔多真理追寻者","parentCard":null,"ids":null,"legacyKeywords":"随从,稀有,外域,圣骑士,嘲讽,战吼","code":"56556-aldor-truthseeker","artist":"Mauricio Herrera","description":"<b>嘲讽，战吼：</b> 在本局对战中，你的圣契的法力值消耗减少（2）点。","consume":0,"cropImage":"https://hearthstone.nosdn.127.net/hearthstone/9b2fd7450501b9358ff85c3465005286aeb77d180e33e3911a09321d0fa110e3.png","gain":0,"classId":5,"cardEffect":"taunt,battlecry","tier":null,"attack":4,"imageUrl":"https://hearthstone.nosdn.127.net/hearthstone/7b6671bdae31cbf3c6edb7a32bf96b7cd4d66a56a831cf2f548131bfc8ea633c.png","cardRarity":"rare","cardSetId":1414,"minionTypeId":null,"cost":5,"cardCode":"","cardType":"minion","standardCard":true,"health":6,"updateTime":null,"classicCard":false,"parentId":null,"cardMultiClass":[],"createTime":null,"minionType":null,"imageGold":"","artistName":"Mauricio Herrera","availableClassIds":[5],"manaCost":5,"wildCard":true},{"cardRace":"rare","standard":1,"flavorText":"心怀荣耀的圣骑士在战斗中从不屑于打脸……直到下个回合！","collectible":1,"keywords":[],"battlegrounds":null,"keywordIds":null,"pic":"https://hearthstone.nosdn.127.net/hearthstone/9ed57772663e713e545250c69760d08ce43b2daf2507f1c2c2165919ef23f858.png","spellSchoolId":5,"childCards":null,"childIds":null,"multiClassIds":[],"golden":0,"id":59583,"cardTypeId":5,"text":"使一个随从获得+8/+8，在本回合中无法攻击英雄。","cardClass":"paladin","slug":"59583-blessing-of-authority","image":"https://hearthstone.nosdn.127.net/hearthstone/9ed57772663e713e545250c69760d08ce43b2daf2507f1c2c2165919ef23f858.png","neutralClass":null,"durability":null,"rarityId":3,"dustValue":null,"armor":null,"background":"心怀荣耀的圣骑士在战斗中从不屑于打脸……直到下个回合！","cardSet":"scholomance-academy","craftingCost":null,"cardId":59583,"availableGameModes":["constructed","duels"],"name":"威能祝福","parentCard":null,"ids":null,"legacyKeywords":"法术,稀有,通灵学园,圣骑士","code":"59583-blessing-of-authority","artist":"Jim Nelson","description":"使一个随从获得+8/+8，在本回合中无法攻击英雄。","consume":0,"cropImage":"https://hearthstone.nosdn.127.net/hearthstone/8dd624f4adfc8bc7228d58c0de53c44913a3115273866643eef9d5e3c7178f37.png","gain":0,"classId":5,"cardEffect":"","tier":null,"attack":null,"imageUrl":"https://hearthstone.nosdn.127.net/hearthstone/9ed57772663e713e545250c69760d08ce43b2daf2507f1c2c2165919ef23f858.png","cardRarity":"rare","cardSetId":1443,"minionTypeId":null,"cost":5,"cardCode":"","cardType":"spell","standardCard":true,"health":null,"updateTime":null,"classicCard":false,"parentId":null,"cardMultiClass":[],"createTime":null,"minionType":null,"imageGold":"","artistName":"Jim Nelson","availableClassIds":[5],"manaCost":5,"wildCard":true}],"curPage":21,"prePage":20,"nextPage":22,"totalPage":29,"totalPerClass":{"demonhunter":109,"hunter":230,"druid":230,"shaman":230,"paladin":230,"warrior":230,"rogue":232,"mage":231,"priest":237,"warlock":232,"neutral":1048},"pageSize":8,"curCardClass":"paladin"}