{"total":230,"cards":[{"cardRace":"rare","standard":0,"flavorText":"琥珀编织技术只有在特殊的职业技校才能学到。","collectible":1,"keywords":["battlecry"],"battlegrounds":null,"keywordIds":[8],"pic":"https://hearthstone.nosdn.127.net/hearthstone/8b22461c8dc227c306e6386db40898a273d9d8bd701b702fafe8166c525030f6.png","spellSchoolId":null,"childCards":null,"childIds":null,"multiClassIds":[],"golden":0,"id":38621,"cardTypeId":4,"text":"<b>战吼：</b> 如果你的克苏恩至少具有10点攻击力，便获得+5生命值。","cardClass":"druid","slug":"38621-klaxxi-amber-weaver","image":"https://hearthstone.nosdn.127.net/hearthstone/8b22461c8dc227c306e6386db40898a273d9d8bd701b702fafe8166c525030f6.png","neutralClass":null,"durability":null,"rarityId":3,"dustValue":null,"armor":null,"background":"琥珀编织技术只有在特殊的职业技校才能学到。","cardSet":"wotog","craftingCost":null,"cardId":38621,"availableGameModes":["constructed","duels"],"name":"卡拉克西织珀者","parentCard":null,"ids":null,"legacyKeywords":"随从,稀有,上古之神,德鲁伊,战吼","code":"38621-klaxxi-amber-weaver","artist":"Cole Eastburn","description":"<b>战吼：</b> 如果你的克苏恩至少具有10点攻击力，便获得+5生命值。","consume":0,"cropImage":"https://hearthstone.nosdn.127.net/hearthstone/f9b5800c6887536ecc88484c13bf943ab5dc26c002f806ef0425963994eba1ff.jpg","gain":0,"classId":2,"cardEffect":"battlecry","tier":null,"attack":4,"imageUrl":"https://hearthstone.nosdn.127.net/hearthstone/8b22461c8dc227c306e6386db40898a273d9d8bd701b702fafe8166c525030f6.png","cardRarity":"rare","cardSetId":21,"minionTypeId":null,"cost":4,"cardCode":"","cardType":"minion","standardCard":false,"health":5,"updateTime":null,"classicCard":false,"parentId":null,"cardMultiClass":[],"createTime":null,"minionType":null,"imageGold":"","artistName":"Cole Eastburn","availableClassIds":[2],"manaCost":4,"wildCard":true},{"cardRace":"common","standard":1,"flavorText":"专业技能推出之后，科多兽的种群数量遭到了毁灭性打击。","collectible":1,"keywords":["taunt","deathrattle"],"battlegrounds":null,"keywordIds":[1,12],"pic":"https://hearthstone.nosdn.127.net/hearthstone/9a95e162e53f6211516eba4f1655b366f183f8a0777022998d25e95a2c751e01.png","spellSchoolId":null,"childCards":null,"childIds":null,"multiClassIds":[],"golden":0,"id":63029,"cardTypeId":4,"text":"<b>嘲讽</b>，<b>亡语：</b>获得5点护甲值。","cardClass":"druid","slug":"63029-thickhide-kodo","image":"https://hearthstone.nosdn.127.net/hearthstone/9a95e162e53f6211516eba4f1655b366f183f8a0777022998d25e95a2c751e01.png","neutralClass":null,"durability":null,"rarityId":1,"dustValue":null,"armor":null,"background":"专业技能推出之后，科多兽的种群数量遭到了毁灭性打击。","cardSet":"forged-in-the-barrens","craftingCost":null,"cardId":63029,"availableGameModes":["constructed","duels"],"name":"厚皮科多兽","parentCard":null,"ids":null,"legacyKeywords":"随从,普通,野兽,贫瘠之地,德鲁伊,嘲讽,亡语","code":"63029-thickhide-kodo","artist":"Zoltan Boros","description":"<b>嘲讽</b>，<b>亡语：</b>获得5点护甲值。","consume":0,"cropImage":"https://hearthstone.nosdn.127.net/hearthstone/69a785b782db121d149a6e4748818cf64197079cb365c03b17b8d5c917b1f861.png","gain":0,"classId":2,"cardEffect":"taunt,deathrattle","tier":null,"attack":3,"imageUrl":"https://hearthstone.nosdn.127.net/hearthstone/9a95e162e53f6211516eba4f1655b366f183f8a0777022998d25e95a2c751e01.png","cardRarity":"common","cardSetId":1525,"minionTypeId":20,"cost":4,"cardCode":"","cardType":"minion","standardCard":true,"health":5,"updateTime":null,"classicCard":false,"parentId":null,"cardMultiClass":[],"createTime":null,"minionType":"beast","imageGold":"","artistName":"Zoltan Boros","availableClassIds":[2],"manaCost":4,"wildCard":true},{"cardRace":"rare","standard":0,"flavorText":"他是玩三壳游戏的高手，你永远也猜不中球在哪个壳下面。","collectible":1,"keywords":["taunt","stealth"],"battlegrounds":null,"keywordIds":[1,6],"pic":"https://hearthstone.nosdn.127.net/hearthstone/ed9a4eca83215bac6342c813ea961b6971bf0016d7402734ef3ab7721d98e9a4.png","spellSchoolId":null,"childCards":[{"flavorText":"","collectible":0,"battlegrounds":null,"keywordIds":[6],"spellSchoolId":null,"cropImage":null,"classId":2,"tier":null,"childIds":null,"attack":5,"multiClassIds":[],"cardSetId":27,"cardTypeId":4,"id":40974,"text":"<b>潜行</b>","minionTypeId":20,"slug":"40974-shellshifter","image":"https://hearthstone.nosdn.127.net/hearthstone/8c0a495f1c0180702f16d99049e724e3b39d60b4fc01513095c8b196b077c535.png","durability":null,"health":3,"parentId":40973,"rarityId":3,"armor":null,"availableGameModes":["constructed"],"name":"变形神龟","imageGold":"","artistName":"Matt Dixon","availableClassIds":[2],"manaCost":4},{"flavorText":"","collectible":0,"battlegrounds":null,"keywordIds":[1],"spellSchoolId":null,"cropImage":null,"classId":2,"tier":null,"childIds":null,"attack":3,"multiClassIds":[],"cardSetId":27,"cardTypeId":4,"id":40975,"text":"<b>嘲讽</b>","minionTypeId":20,"slug":"40975-shellshifter","image":"https://hearthstone.nosdn.127.net/hearthstone/2a83e7312145c5e7e2b44af0b50d062e5a2698064a759143ab9856c11c0cfc83.png","durability":null,"health":5,"parentId":null,"rarityId":3,"armor":null,"availableGameModes":["constructed"],"name":"变形神龟","imageGold":"","artistName":"Matt Dixon","availableClassIds":[2],"manaCost":4},{"flavorText":"","collectible":0,"battlegrounds":null,"keywordIds":[1,6],"spellSchoolId":null,"cropImage":null,"classId":2,"tier":null,"childIds":null,"attack":5,"multiClassIds":[],"cardSetId":27,"cardTypeId":4,"id":40976,"text":"<b>潜行</b> <b>嘲讽</b>","minionTypeId":20,"slug":"40976-shellshifter","image":"https://hearthstone.nosdn.127.net/hearthstone/f622dc4452ead80dcc2f27b4d5d045fafb397a198a6529b21ca2718ab321217c.png","durability":null,"health":5,"parentId":null,"rarityId":3,"armor":null,"availableGameModes":["constructed"],"name":"变形神龟","imageGold":"","artistName":"Matt Dixon","availableClassIds":[2],"manaCost":4},{"flavorText":"","collectible":0,"battlegrounds":null,"keywordIds":null,"spellSchoolId":null,"cropImage":null,"classId":2,"tier":null,"childIds":null,"attack":5,"multiClassIds":[],"cardSetId":27,"cardTypeId":4,"id":40977,"text":"<b>潜行</b>","minionTypeId":20,"slug":"40977-raptor-form","image":"https://hearthstone.nosdn.127.net/hearthstone/ad960a830bc6618b5a6200ab2d7767150bb625945b2596dc1b8e9b30d4ee28c3.png","durability":null,"health":3,"parentId":40973,"rarityId":3,"armor":null,"availableGameModes":["constructed"],"name":"迅猛龙形态","imageGold":"","artistName":"Matt Dixon","availableClassIds":[2],"manaCost":4},{"flavorText":"","collectible":0,"battlegrounds":null,"keywordIds":null,"spellSchoolId":null,"cropImage":null,"classId":2,"tier":null,"childIds":null,"attack":3,"multiClassIds":[],"cardSetId":27,"cardTypeId":4,"id":40978,"text":"<b>嘲讽</b>","minionTypeId":20,"slug":"40978-direhorn-form","image":"https://hearthstone.nosdn.127.net/hearthstone/ef433c268df65c63f9d0fbccbe97ee3a077b57f7e83ae46e3128fd2dfed286e7.png","durability":null,"health":5,"parentId":40973,"rarityId":3,"armor":null,"availableGameModes":["constructed"],"name":"恐角龙形态","imageGold":"","artistName":"Matt Dixon","availableClassIds":[2],"manaCost":4}],"childIds":[40974,40975,40976,40977,40978],"multiClassIds":[],"golden":0,"id":40973,"cardTypeId":4,"text":"<b>抉择：</b>将该随从变形成为5/3并具有<b>潜行</b>；或者将该随从变形成为3/5并具有<b>嘲讽</b>。","cardClass":"druid","slug":"40973-shellshifter","image":"https://hearthstone.nosdn.127.net/hearthstone/ed9a4eca83215bac6342c813ea961b6971bf0016d7402734ef3ab7721d98e9a4.png","neutralClass":null,"durability":null,"rarityId":3,"dustValue":null,"armor":null,"background":"他是玩三壳游戏的高手，你永远也猜不中球在哪个壳下面。","cardSet":"ungoro","craftingCost":null,"cardId":40973,"availableGameModes":["constructed","duels"],"name":"变形神龟","parentCard":null,"ids":null,"legacyKeywords":"随从,稀有,安戈洛,德鲁伊,嘲讽,潜行","code":"40973-shellshifter","artist":"Matt Dixon","description":"<b>抉择：</b>将该随从变形成为5/3并具有<b>潜行</b>；或者将该随从变形成为3/5并具有<b>嘲讽</b>。","consume":0,"cropImage":"https://hearthstone.nosdn.127.net/hearthstone/b63dca9d660918dd42559c6c677ced8455010211be5a241ab294be01b4aacb62.png","gain":0,"classId":2,"cardEffect":"taunt,stealth","tier":null,"attack":3,"imageUrl":"https://hearthstone.nosdn.127.net/hearthstone/ed9a4eca83215bac6342c813ea961b6971bf0016d7402734ef3ab7721d98e9a4.png","cardRarity":"rare","cardSetId":27,"minionTypeId":null,"cost":4,"cardCode":"","cardType":"minion","standardCard":false,"health":3,"updateTime":null,"classicCard":false,"parentId":null,"cardMultiClass":[],"createTime":null,"minionType":null,"imageGold":"","artistName":"Matt Dixon","availableClassIds":[2],"manaCost":4,"wildCard":true},{"cardRace":"rare","standard":1,"flavorText":"想让树妖在不踩到花花草草的前提下管理园地，实在有点难。","collectible":1,"keywords":["taunt","battlecry"],"battlegrounds":null,"keywordIds":[1,8],"pic":"https://hearthstone.nosdn.127.net/hearthstone/a2548745fc0768912fbdd6b4e2be2d12aa645686a8db69471a2a75892aafa3a0.png","spellSchoolId":null,"childCards":null,"childIds":null,"multiClassIds":[2,8],"golden":0,"id":59553,"cardTypeId":4,"text":"<b>嘲讽，战吼：</b>如果你的手牌中有法力值消耗大于或等于（5）点的法术牌，恢复5点生命值。","cardClass":"","slug":"59553-groundskeeper","image":"https://hearthstone.nosdn.127.net/hearthstone/a2548745fc0768912fbdd6b4e2be2d12aa645686a8db69471a2a75892aafa3a0.png","neutralClass":null,"durability":null,"rarityId":3,"dustValue":null,"armor":null,"background":"想让树妖在不踩到花花草草的前提下管理园地，实在有点难。","cardSet":"scholomance-academy","craftingCost":null,"cardId":59553,"availableGameModes":["constructed","duels"],"name":"园地管理员","parentCard":null,"ids":null,"legacyKeywords":"随从,稀有,通灵学园,德鲁伊,萨满祭司,嘲讽,战吼","code":"59553-groundskeeper","artist":"Eva Widermann","description":"<b>嘲讽，战吼：</b>如果你的手牌中有法力值消耗大于或等于（5）点的法术牌，恢复5点生命值。","consume":0,"cropImage":"https://hearthstone.nosdn.127.net/hearthstone/e89362412a34ad19c54ed97ce457ab8103137bef9d710dc9792a8c347a37468c.png","gain":0,"classId":2,"cardEffect":"taunt,battlecry","tier":null,"attack":4,"imageUrl":"https://hearthstone.nosdn.127.net/hearthstone/a2548745fc0768912fbdd6b4e2be2d12aa645686a8db69471a2a75892aafa3a0.png","cardRarity":"rare","cardSetId":1443,"minionTypeId":null,"cost":4,"cardCode":"","cardType":"minion","standardCard":true,"health":5,"updateTime":null,"classicCard":false,"parentId":null,"cardMultiClass":["druid","shaman"],"createTime":null,"minionType":null,"imageGold":"","artistName":"Eva Widermann","availableClassIds":[2,8],"manaCost":4,"wildCard":true},{"cardRace":"rare","standard":0,"flavorText":"“你好啊，我的小树树……该洗澡澡啦。”","collectible":1,"keywords":["battlecry"],"battlegrounds":null,"keywordIds":[8],"pic":"https://hearthstone.nosdn.127.net/hearthstone/15150dfe60dad2b3f6294f8383738e7d9909b3491912d8a446979aa5f73ebdae.png","spellSchoolId":null,"childCards":[{"flavorText":"","collectible":0,"battlegrounds":null,"keywordIds":null,"spellSchoolId":null,"cropImage":null,"classId":2,"tier":null,"childIds":null,"attack":2,"multiClassIds":[],"cardSetId":1158,"cardTypeId":4,"id":54541,"text":"","minionTypeId":null,"slug":"54541-treant","image":"https://hearthstone.nosdn.127.net/hearthstone/d16eb146bda81eb4c33861b9cd501aafc9c58353a3ec1e375b9bc3a8c1e50649.png","durability":null,"health":2,"parentId":53613,"rarityId":null,"armor":null,"availableGameModes":["constructed"],"name":"树人","imageGold":"","artistName":"Ivan Fomin","availableClassIds":[2],"manaCost":2}],"childIds":[54541],"multiClassIds":[],"golden":0,"id":53613,"cardTypeId":4,"text":"<b>战吼：</b>如果你的手牌中有法力值消耗大于或等于（5）点的法术牌，便召唤两个2/2的树人。","cardClass":"druid","slug":"53613-garden-gnome","image":"https://hearthstone.nosdn.127.net/hearthstone/15150dfe60dad2b3f6294f8383738e7d9909b3491912d8a446979aa5f73ebdae.png","neutralClass":null,"durability":null,"rarityId":3,"dustValue":null,"armor":null,"background":"“你好啊，我的小树树……该洗澡澡啦。”","cardSet":"saviors-of-uldum","craftingCost":null,"cardId":53613,"availableGameModes":["constructed","arena"],"name":"园艺侏儒","parentCard":null,"ids":null,"legacyKeywords":"随从,稀有,奥丹姆,德鲁伊,战吼","code":"53613-garden-gnome","artist":"Ivan Fomin","description":"<b>战吼：</b>如果你的手牌中有法力值消耗大于或等于（5）点的法术牌，便召唤两个2/2的树人。","consume":0,"cropImage":"https://hearthstone.nosdn.127.net/hearthstone/047525e280a75821b46ce5441c3aa870c59e17f483dc84f6ca8b64e3890f56cf.png","gain":0,"classId":2,"cardEffect":"battlecry","tier":null,"attack":2,"imageUrl":"https://hearthstone.nosdn.127.net/hearthstone/15150dfe60dad2b3f6294f8383738e7d9909b3491912d8a446979aa5f73ebdae.png","cardRarity":"rare","cardSetId":1158,"minionTypeId":null,"cost":4,"cardCode":"","cardType":"minion","standardCard":false,"health":3,"updateTime":null,"classicCard":false,"parentId":null,"cardMultiClass":[],"createTime":null,"minionType":null,"imageGold":"https://hearthstone.nosdn.127.net/hearthstone/d19224e46d052230096168dea4b8b5e7329b5f6dec43bb7d8b74a566cfefa162.png","artistName":"Ivan Fomin","availableClassIds":[2],"manaCost":4,"wildCard":true},{"cardRace":"legendary","standard":1,"flavorText":"当太阳运行到月亮和艾泽拉斯之间时……发生的就是灾难现象了。","collectible":1,"keywords":["battlecry"],"battlegrounds":null,"keywordIds":[8],"pic":"https://hearthstone.nosdn.127.net/hearthstone/b81f3d82f88f0f3997710237fd58eacaa677eaca26761e6fd36b61fcfbff06b9.png","spellSchoolId":null,"childCards":[{"flavorText":"当艾泽拉斯运行到太阳和月亮之间时发生的现象。","collectible":1,"battlegrounds":null,"keywordIds":null,"spellSchoolId":1,"cropImage":"https://hearthstone.nosdn.127.net/hearthstone/17bc74de18b0fa167cf64c3c00cb6ba27e1b1addaa5cb11ed59bee63d9a4d7f8.png","classId":2,"tier":null,"childIds":null,"attack":null,"multiClassIds":[],"cardSetId":1466,"cardTypeId":5,"id":61449,"text":"对一个随从造成 3点伤害。在本回合中，你施放的下一个法术的法力值消耗减少（2）点。","minionTypeId":null,"slug":"61449-lunar-eclipse","image":"https://hearthstone.nosdn.127.net/hearthstone/d323f97c581edc06518e664650ec67f9dcb9cdbe02ba7e2aa01c046e3ee08f44.png","durability":null,"health":null,"parentId":null,"rarityId":1,"armor":null,"availableGameModes":["constructed","duels"],"name":"月蚀","imageGold":"","artistName":"Jun Yan","availableClassIds":[2],"manaCost":2},{"flavorText":"当月亮运行到太阳和艾泽拉斯之间时发生的现象。","collectible":1,"battlegrounds":null,"keywordIds":null,"spellSchoolId":4,"cropImage":"https://hearthstone.nosdn.127.net/hearthstone/9f975c11e71c27a59a828e36072d0ef97e9793487c2f76c8dc68f8539d740f0b.png","classId":2,"tier":null,"childIds":null,"attack":null,"multiClassIds":[],"cardSetId":1466,"cardTypeId":5,"id":61450,"text":"在本回合中，你的下一个法术将施放两次。","minionTypeId":null,"slug":"61450-solar-eclipse","image":"https://hearthstone.nosdn.127.net/hearthstone/176e285aadbb6a6ccdf0bd98d4d60f90ee3411663355005b5d5ec38b9d48ab2d.png","durability":null,"health":null,"parentId":null,"rarityId":1,"armor":null,"availableGameModes":["constructed","duels"],"name":"日蚀","imageGold":"","artistName":"Jun Yan","availableClassIds":[2],"manaCost":2}],"childIds":[61449,61450],"multiClassIds":[],"golden":0,"id":61605,"cardTypeId":4,"text":"<b>战吼：</b> 将一张日蚀和一张月蚀置入你的手牌。","cardClass":"druid","slug":"61605-kiri-chosen-of-elune","image":"https://hearthstone.nosdn.127.net/hearthstone/b81f3d82f88f0f3997710237fd58eacaa677eaca26761e6fd36b61fcfbff06b9.png","neutralClass":null,"durability":null,"rarityId":5,"dustValue":null,"armor":null,"background":"当太阳运行到月亮和艾泽拉斯之间时……发生的就是灾难现象了。","cardSet":"madness-at-the-darkmoon-faire","craftingCost":null,"cardId":61605,"availableGameModes":["constructed","duels"],"name":"基利，艾露恩之眷","parentCard":null,"ids":null,"legacyKeywords":"随从,传说,暗月马戏团,德鲁伊,战吼","code":"61605-kiri-chosen-of-elune","artist":"Paul Mafayon","description":"<b>战吼：</b> 将一张日蚀和一张月蚀置入你的手牌。","consume":0,"cropImage":"https://hearthstone.nosdn.127.net/hearthstone/fb424b3d87711e49ea4252806961ee0feef134cd6d3e19d18d9405c21766305a.png","gain":0,"classId":2,"cardEffect":"battlecry","tier":null,"attack":2,"imageUrl":"https://hearthstone.nosdn.127.net/hearthstone/b81f3d82f88f0f3997710237fd58eacaa677eaca26761e6fd36b61fcfbff06b9.png","cardRarity":"legendary","cardSetId":1466,"minionTypeId":null,"cost":4,"cardCode":"","cardType":"minion","standardCard":true,"health":2,"updateTime":null,"classicCard":false,"parentId":null,"cardMultiClass":[],"createTime":null,"minionType":null,"imageGold":"","artistName":"Paul Mafayon","availableClassIds":[2],"manaCost":4,"wildCard":true},{"cardRace":"rare","standard":0,"flavorText":"先来两个开胃菜。","collectible":1,"keywords":[],"battlegrounds":null,"keywordIds":null,"pic":"https://hearthstone.nosdn.127.net/hearthstone/23a6fbd72d1cebfebfed9c610b6d424727ba5ead7d4b7af2e4e515d0e39c56f6.png","spellSchoolId":null,"childCards":null,"childIds":null,"multiClassIds":[],"golden":0,"id":49994,"cardTypeId":5,"text":"从你的牌库中抽一张野兽牌。将其生命值翻倍。","cardClass":"druid","slug":"49994-predatory-instincts","image":"https://hearthstone.nosdn.127.net/hearthstone/23a6fbd72d1cebfebfed9c610b6d424727ba5ead7d4b7af2e4e515d0e39c56f6.png","neutralClass":null,"durability":null,"rarityId":3,"dustValue":null,"armor":null,"background":"先来两个开胃菜。","cardSet":"rastakhans-rumble","craftingCost":null,"cardId":49994,"availableGameModes":["constructed"],"name":"掠食本能","parentCard":null,"ids":null,"legacyKeywords":"法术,稀有,大乱斗,德鲁伊","code":"49994-predatory-instincts","artist":"Clint Langley","description":"从你的牌库中抽一张野兽牌。将其生命值翻倍。","consume":0,"cropImage":"https://hearthstone.nosdn.127.net/hearthstone/c4e6ad43c05a73da0e9b3f4d5600f863eedaee242199ffcfcc6407b264c6cb69.png","gain":0,"classId":2,"cardEffect":"","tier":null,"attack":null,"imageUrl":"https://hearthstone.nosdn.127.net/hearthstone/23a6fbd72d1cebfebfed9c610b6d424727ba5ead7d4b7af2e4e515d0e39c56f6.png","cardRarity":"rare","cardSetId":1129,"minionTypeId":null,"cost":4,"cardCode":"","cardType":"spell","standardCard":false,"health":null,"updateTime":null,"classicCard":false,"parentId":null,"cardMultiClass":[],"createTime":null,"minionType":null,"imageGold":"https://hearthstone.nosdn.127.net/hearthstone/645d3970e7f0ec14adc428253c0e5bf096cbf7b3576a19d4d95c7965272a21aa.png","artistName":"Clint Langley","availableClassIds":[2],"manaCost":4,"wildCard":true},{"cardRace":"rare","standard":0,"flavorText":"一般说来，你不把嘴里的肉嚼完，是不舍得变回人形态的。","collectible":1,"keywords":[],"battlegrounds":null,"keywordIds":null,"pic":"https://hearthstone.nosdn.127.net/hearthstone/e035d8ac52f9931b4faf26434ba0e0104eb25ecf8638e0f64b605e2b6c88bec7.png","spellSchoolId":null,"childCards":null,"childIds":null,"multiClassIds":[],"golden":0,"id":577,"cardTypeId":5,"text":"使你的英雄获得4点护甲值，并在本回合中获得 +4攻击力。","cardClass":"druid","slug":"577-bite","image":"https://hearthstone.nosdn.127.net/hearthstone/e035d8ac52f9931b4faf26434ba0e0104eb25ecf8638e0f64b605e2b6c88bec7.png","neutralClass":null,"durability":null,"rarityId":3,"dustValue":null,"armor":null,"background":"一般说来，你不把嘴里的肉嚼完，是不舍得变回人形态的。","cardSet":"legacy","craftingCost":null,"cardId":577,"availableGameModes":["constructed","arena","duels"],"name":"撕咬","parentCard":null,"ids":null,"legacyKeywords":"法术,稀有,德鲁伊","code":"577-bite","artist":"MAR Studio","description":"使你的英雄获得4点护甲值，并在本回合中获得 +4攻击力。","consume":0,"cropImage":"https://hearthstone.nosdn.127.net/hearthstone/f40299dc51aa384fa06992e074ff582ca3b7128ec9ed1dfe64580148049b8be1.png","gain":0,"classId":2,"cardEffect":"","tier":null,"attack":null,"imageUrl":"https://hearthstone.nosdn.127.net/hearthstone/e035d8ac52f9931b4faf26434ba0e0104eb25ecf8638e0f64b605e2b6c88bec7.png","cardRarity":"rare","cardSetId":3,"minionTypeId":null,"cost":4,"cardCode":"","cardType":"spell","standardCard":false,"health":null,"updateTime":null,"classicCard":false,"parentId":null,"cardMultiClass":[],"createTime":null,"minionType":null,"imageGold":"https://hearthstone.nosdn.127.net/hearthstone/337952c9e5404c0ed137858c6441e018f44af3971c91a3cf39e3691aa4810b6d.png","artistName":"MAR Studio","availableClassIds":[2],"manaCost":4,"wildCard":true}],"curPage":15,"prePage":14,"nextPage":16,"totalPage":29,"totalPerClass":{"demonhunter":109,"hunter":230,"druid":230,"shaman":230,"paladin":230,"warrior":230,"rogue":232,"mage":231,"priest":237,"warlock":232,"neutral":1048},"pageSize":8,"curCardClass":"druid"}